{"hp": [50, 50, 50, 50, 50, 50, 50, 50, 50, 50, 50, 50, 50, 50, 50, 50, 50, 50, 50, 50], "xCoord": [7, 7, 6, 6, 6, 6, 6, 6, 6, 6, 6, 6, 6, 6, 6, 6, 6, 6, 6, 6], "yCoord": [0, 0, 0, 0, 0, 0, 0, 0, 0, 0, 0, 0, 0, 0, 0, 0, 0, 0, 0, 0], "state": ["NoMove", "NoMove", "move", "move", "beartrap", "beartrap", "recover", "recover", "heavy", "heavy", "recover", "recover", "NoMove", "NoMove", "NoMove", "NoMove", "NoMove", "NoMove", "NoMove", "NoMove"], "actionType": ["NoMove", "NoMove", [1, 0], "Fill", "activate", "Fill", null, "Fill", "activate", "Fill", null, "Fill", "NoMove", "Fill", "NoMove", "Fill", "NoMove", "Fill", "NoMove", "Fill"], "stun": [0, 0, 0, 0, 0, 0, 0, 0, 0, 0, 0, 0, 0, 0, 0, 0, 0, 0, 0, 0], "midair": [false, false, false, false, false, false, false, false, false, false, false, false, false, false, false, false, false, false, false, false], "falling": [false, false, false, false, false, false, false, false, false, false, false, false, false, false, false, false, false, false, false, false], "direction": [1, 1, 1, 1, 1, 1, 1, 1, 1, 1, 1, 1, 1, 1, 1, 1, 1, 1, 1, 1], "ProjectileType": "beartrap", "projXCoord": [-1, -1, -1, -1, 7, 7, -1, -1, -1, -1, -1, -1, -1, -1, -1, -1, -1, -1, -1, -1], "projYCoord": [-1, -1, -1, -1, 0, 0, -1, -1, -1, -1, -1, -1, -1, -1, -1, -1, -1, -1, -1, -1]}